davteutil/__init__.py
davteutil/davteutil.py
davteutil/utilities.py
davteutil-1.1.17.dist-info/LICENSE
davteutil-1.1.17.dist-info/METADATA
davteutil-1.1.17.dist-info/WHEEL
davteutil-1.1.17.dist-info/top_level.txt
davteutil-1.1.17.dist-info/RECORD
