Metadata-Version: 2.1
Name: davteutil
Version: 1.1.17
Summary: Useful general purpose functions and classes, used by Davte.
Home-page: https://bitbucket.org/davte/davteutil
Author: Davide Testa
Author-email: davte@libero.it
License: GNU General Public License v3.0
Keywords: utilities davte davtelepot
Platform: any
Classifier: Development Status :: 3 - Alpha
Classifier: Framework :: AsyncIO
Classifier: Intended Audience :: Developers
Classifier: License :: OSI Approved :: GNU Lesser General Public License v3 (LGPLv3)
Classifier: Natural Language :: English
Classifier: Operating System :: OS Independent
Classifier: Programming Language :: Python :: 3 :: Only
Classifier: Topic :: Utilities
Requires-Dist: aiohttp (>=3.4.4)
Requires-Dist: bs4 (>=0.0.1)
